ccpulse/__init__.py
ccpulse/__main__.py
ccpulse/analyzer.py
ccpulse/cli.py
ccpulse/display.py
ccpulse/loader.py
ccpulse-0.3.1.dist-info/METADATA
ccpulse-0.3.1.dist-info/WHEEL
ccpulse-0.3.1.dist-info/entry_points.txt
ccpulse-0.3.1.dist-info/licenses/LICENSE
ccpulse-0.3.1.dist-info/RECORD
