Metadata-Version: 2.4
Name: ccpulse
Version: 0.3.1
Summary: Track your custom Skills and Subagents usage in Claude Code
Project-URL: Homepage, https://github.com/dukbong/ccpulse
Project-URL: Repository, https://github.com/dukbong/ccpulse
Project-URL: Issues, https://github.com/dukbong/ccpulse/issues
Author: dukbong
License-Expression: MIT
License-File: LICENSE
Keywords: analytics,anthropic,claude,cli,statistics
Classifier: Development Status :: 4 - Beta
Classifier: Environment :: Console
Classifier: Intended Audience :: Developers
Classifier: License :: OSI Approved :: MIT License
Classifier: Operating System :: OS Independent
Classifier: Programming Language :: Python :: 3
Classifier: Programming Language :: Python :: 3.10
Classifier: Programming Language :: Python :: 3.11
Classifier: Programming Language :: Python :: 3.12
Classifier: Programming Language :: Python :: 3.13
Classifier: Topic :: Utilities
Requires-Python: >=3.10
Requires-Dist: rich>=13.0.0
Requires-Dist: typer>=0.9.0
